dockerd/__init__.py
dockerd-1.0.0.dist-info/DESCRIPTION.rst
dockerd-1.0.0.dist-info/METADATA
dockerd-1.0.0.dist-info/RECORD
dockerd-1.0.0.dist-info/WHEEL
dockerd-1.0.0.dist-info/metadata.json
dockerd-1.0.0.dist-info/top_level.txt
dockerd-1.0.0.dist-info/zip-safe
