Metadata-Version: 2.0
Name: dockerd
Version: 1.0.0
Summary: Run Docker daemon as a subprocess
Home-page: https://gitlab.com/lew21/dockerd-py
Author: Linus Lewandowski
Author-email: linus@lew21.net
License: UNKNOWN
Keywords: docker
Platform: UNKNOWN
Classifier: Development Status :: 5 - Production/Stable
Classifier: Environment :: Other Environment
Classifier: Intended Audience :: Developers
Classifier: Operating System :: OS Independent
Classifier: Programming Language :: Python
Classifier: Programming Language :: Python :: 3.5
Classifier: Programming Language :: Python :: 3.6
Classifier: Topic :: Utilities
Classifier: License :: OSI Approved :: MIT License
